terminaltexteffects/__init__.py
terminaltexteffects/__main__.py
terminaltexteffects/py.typed
terminaltexteffects/effects/__init__.py
terminaltexteffects/effects/effect_beams.py
terminaltexteffects/effects/effect_binarypath.py
terminaltexteffects/effects/effect_blackhole.py
terminaltexteffects/effects/effect_bouncyballs.py
terminaltexteffects/effects/effect_bubbles.py
terminaltexteffects/effects/effect_burn.py
terminaltexteffects/effects/effect_colorshift.py
terminaltexteffects/effects/effect_crumble.py
terminaltexteffects/effects/effect_decrypt.py
terminaltexteffects/effects/effect_errorcorrect.py
terminaltexteffects/effects/effect_expand.py
terminaltexteffects/effects/effect_fireworks.py
terminaltexteffects/effects/effect_highlight.py
terminaltexteffects/effects/effect_laseretch.py
terminaltexteffects/effects/effect_matrix.py
terminaltexteffects/effects/effect_middleout.py
terminaltexteffects/effects/effect_orbittingvolley.py
terminaltexteffects/effects/effect_overflow.py
terminaltexteffects/effects/effect_pour.py
terminaltexteffects/effects/effect_print.py
terminaltexteffects/effects/effect_rain.py
terminaltexteffects/effects/effect_random_sequence.py
terminaltexteffects/effects/effect_rings.py
terminaltexteffects/effects/effect_scattered.py
terminaltexteffects/effects/effect_slice.py
terminaltexteffects/effects/effect_slide.py
terminaltexteffects/effects/effect_spotlights.py
terminaltexteffects/effects/effect_spray.py
terminaltexteffects/effects/effect_swarm.py
terminaltexteffects/effects/effect_sweep.py
terminaltexteffects/effects/effect_synthgrid.py
terminaltexteffects/effects/effect_unstable.py
terminaltexteffects/effects/effect_vhstape.py
terminaltexteffects/effects/effect_waves.py
terminaltexteffects/effects/effect_wipe.py
terminaltexteffects/engine/__init__.py
terminaltexteffects/engine/animation.py
terminaltexteffects/engine/base_character.py
terminaltexteffects/engine/base_effect.py
terminaltexteffects/engine/motion.py
terminaltexteffects-0.12.2.dist-info/METADATA
terminaltexteffects-0.12.2.dist-info/WHEEL
terminaltexteffects-0.12.2.dist-info/entry_points.txt
terminaltexteffects-0.12.2.dist-info/licenses/LICENSE
terminaltexteffects-0.12.2.dist-info/RECORD
