Metadata-Version: 2.4
Name: terminaltexteffects
Version: 0.12.2
Summary: TerminalTextEffects (TTE) is a terminal visual effects engine.
Project-URL: Repository, https://github.com/ChrisBuilds/terminaltexteffects
Project-URL: Documentation, https://chrisbuilds.github.io/terminaltexteffects/
Author-email: Chris <741258@pm.me>
License-Expression: MIT
License-File: LICENSE
Requires-Python: >=3.8
